colombian_grid-0.1.0.dist-info/METADATA
colombian_grid-0.1.0.dist-info/WHEEL
colombian_grid-0.1.0.dist-info/entry_points.txt
colombian_grid-0.1.0.dist-info/licenses/LICENSE
colombian_grid/__init__.py
colombian_grid/core/__init__.py
colombian_grid/core/base/__init__.py
colombian_grid/core/base/interfaces/__init__.py
colombian_grid/core/base/interfaces/base.py
colombian_grid/core/base/interfaces/paratec/__init__.py
colombian_grid/core/base/interfaces/paratec/generators.py
colombian_grid/core/base/interfaces/paratec/hydrology.py
colombian_grid/core/base/interfaces/paratec/transmission.py
colombian_grid/core/base/interfaces/paratec/utils.py
colombian_grid/core/base/interfaces/xm/__init__.py
colombian_grid/core/base/interfaces/xm/fetchers.py
colombian_grid/core/base/interfaces/xm/utils.py
colombian_grid/core/infra/__init__.py
colombian_grid/core/infra/http/__init__.py
colombian_grid/core/infra/http/base.py
colombian_grid/core/infra/http/httpx/__init__.py
colombian_grid/core/infra/http/httpx/async_client.py
colombian_grid/core/paratec/__init__.py
colombian_grid/core/paratec/paratec.py
colombian_grid/core/schemas/__init__.py
colombian_grid/core/schemas/generator.py
colombian_grid/core/schemas/hydrology.py
colombian_grid/core/schemas/transmission.py
colombian_grid/core/schemas/xm.py
colombian_grid/core/xm/__init__.py
colombian_grid/core/xm/xm_client.py
colombian_grid/utils/__init__.py
colombian_grid/utils/data_transform.py
colombian_grid-0.1.0.dist-info/RECORD
