Metadata-Version: 2.1
Name: colombian-grid
Version: 0.1.0
Summary: Extract and process the currently available colombian grid public data
Keywords: colombian,grid,extraction,digitalization
Author-Email: Camilo Camargo <kamilo1494@gmail.com>
Maintainer-Email: Camilo Camargo <kamilo1494@gmail.com>
Requires-Python: >=3.11
Requires-Dist: httpx==0.28.1
Requires-Dist: pydantic==2.10.6
Requires-Dist: pandas>=2.0.0
